sandclock/__init__.py
sandclock/sandclock.py
sandclock-0.1.3.dist-info/WHEEL
sandclock-0.1.3.dist-info/METADATA
sandclock-0.1.3.dist-info/RECORD
